hypothesis_ros/__init__.py
hypothesis_ros/message_fields.py
hypothesis_ros/parameters.py
hypothesis_ros/messages/__init__.py
hypothesis_ros/messages/geometry_msgs.py
hypothesis_ros/messages/sensor_msgs.py
hypothesis_ros/messages/std_msgs.py
hypothesis_ros/messages/stereo_msgs.py
hypothesis_ros/messages/tf2_msgs.py
hypothesis_ros/ros1/__init__.py
hypothesis_ros/ros1/builtin_msg_field_types.py
hypothesis_ros/ros1/geometry_msgs.py
hypothesis_ros/ros1/std_msgs.py
hypothesis_ros-0.3.0.dist-info/LICENSE.txt
hypothesis_ros-0.3.0.dist-info/METADATA
hypothesis_ros-0.3.0.dist-info/RECORD
hypothesis_ros-0.3.0.dist-info/WHEEL
hypothesis_ros-0.3.0.dist-info/top_level.txt
