Metadata-Version: 2.1
Name: hypothesis-ros
Version: 0.3.0
Summary: Property Based Testing for the ROS node level.
Home-page: https://github.com/ros-testing/hypothesis-ros
Author: Florian Kromer
Author-email: florian.kromer@mailbox.org
License: Apache License 2.0
Platform: UNKNOWN
Classifier: Development Status :: 4 - Beta
Classifier: Intended Audience :: Developers
Classifier: License :: OSI Approved :: Apache Software License
Classifier: Programming Language :: Python
Classifier: Programming Language :: Python :: 2
Classifier: Programming Language :: Python :: 2.7
Classifier: Programming Language :: Python :: Implementation :: CPython
Classifier: Programming Language :: Python :: Implementation :: PyPy
Classifier: Topic :: Scientific/Engineering
Classifier: Topic :: Software Development :: Testing
Requires-Dist: hypothesis (>=3.55.1)
Requires-Dist: sphinx (>=1.7.2)
